NseEod/NseEod.py
NseEod/__init__.py
nseeod-0.0.9.dist-info/METADATA
nseeod-0.0.9.dist-info/WHEEL
nseeod-0.0.9.dist-info/top_level.txt
nseeod-0.0.9.dist-info/RECORD
