Metadata-Version: 2.4
Name: NseEod
Version: 0.0.9
Summary: A NSEEOD library to fetch NSE EOD data
Author: Prasad
Requires-Python: >=3.8
Requires-Dist: pandas
Requires-Dist: requests
Requires-Dist: numpy
Requires-Dist: feedparser
Requires-Dist: urllib3
Requires-Dist: gspread
Requires-Dist: oauth2client
Requires-Dist: google-auth
Requires-Dist: schedule
Requires-Dist: pytz
Requires-Dist: beautifulsoup4
Requires-Dist: xlrd
Requires-Dist: openpyxl
Requires-Dist: pyxlsb
Dynamic: author
Dynamic: requires-dist
Dynamic: requires-python
Dynamic: summary
